[
	{
		"text": "已完成",
		"path": "finished",
		"list": [
			"union和继承",
			"自动机和群论",
			"有向无环图上的寄存器分配（一）",
			"unique_ptr的循环引用问题",
			"菜谱作为程序",
			"关于JVM垃圾回收的一些讨论",
			"馅饼咬痕问题"
		]
	},
	{
		"text": "暂时搁置",
		"path": "delayed",
		"list": [
			"工具复杂性",
			"抽象树和依赖图",
			"作用域和控制流",
			"enum，union和switch",
			"索引与实物",
			"数据结构",
			"递归的消除",
			"有向无环图上的寄存器分配（二）",
			"存储系统设计"
		]
	},
	{
		"text": "暂时搁置（二）",
		"path": "delayed-2",
		"list": [
			"什么是值类型",
			"控制字符",
			"图形界面库的设计",
			"层次化文本编辑器的设计",
			"数据和计算",
			"配置文件",
			"数组类型",
			"命令行和图形界面",
			"结构抽象和类型抽象",
			"编辑、编译和运行",
			"编译流程",
			"社交平台的设计",
			"迭代的消除",
			"常量和变量"
		]
	},
	{
		"text": "豆瓣226180635（2020/11/6-2021/11/6）日记存档",
		"path": "douban-archive",
		"list": [
			"常量和变量",
			"馅饼咬痕问题",
			"结构抽象和类型抽象",
			"菜谱作为程序",
			"Azimuth",
			"三维空间翻转变换群",
			"互联网时代的空间邻域",
			"阳台上的蚂蚁洞",
			"编译过程会丢失信息吗？",
			"接口的正交性——以淋浴冷热水开关为例",
			"磨刀与砍柴——一个非常简单的数学问题",
			"“工具”复杂性",
			"先有鸡还是先有蛋——编程语言的“自举”",
			"社交网络中的“握手定理”",
			"先有鸡还是先有蛋？",
			"迭代和递归",
			"——我是早起冠军！ ——不，你不是"
		]
	}
]